MANIFEST.in
README.md
requirements.txt
setup.cfg
setup.py
tests-requirements.txt
make_songbook.egg-info/PKG-INFO
make_songbook.egg-info/SOURCES.txt
make_songbook.egg-info/dependency_links.txt
make_songbook.egg-info/entry_points.txt
make_songbook.egg-info/requires.txt
make_songbook.egg-info/top_level.txt
makesongbook/make_songbook.py
makesongbook/song_library.py
makesongbook/songbook_printer.py
makesongbook/template/book.opf
makesongbook/template/default.css
makesongbook/template/songbook.template.html
makesongbook/template/tox.template.ncx