Metadata-Version: 1.1
Name: make-songbook
Version: 0.0.1
Summary: Digital songbook maker.
Home-page: http://github.com/adericbourg/make-songbook
Author: Alban Dericbourg
Author-email: alban@dericbourg.net
License: GPLv3
Platform: UNKNOWN
Classifier: Intended Audience :: End Users/Desktop
Classifier: License :: OSI Approved :: GNU General Public License v3 (GPLv3)
Classifier: Operating System :: OS Independent
Classifier: Programming Language :: Python
Classifier: Programming Language :: Python :: 3
Classifier: Programming Language :: Python :: 3.5
Classifier: Programming Language :: Python :: 3.6
